[
    {
        "itemId": "Ct0By5Sh_dE",
        "title": "আল্লাহর কাছে পছন্দনীয় যারা | Mizanur Rahman Azhari | সাইবারজায়া কনফারেন্স ২০২৩",
        "lecturer": "Mizanur Rahman Azhari",
        "length": "58:58",
        "lecturerId": "2"
    },
    {
        "itemId": "jHZej8kqURc",
        "title": "জান্নাতি নারী পুরুষের বৈশিষ্ট্য | Mizanur Rahman Azhari | Gender Equality in terms of getting reward",
        "lecturer": "Mizanur Rahman Azhari",
        "length": "1:19:39",
        "lecturerId": "2"
    },
    {
        "itemId": "HCKeHaNN-M0",
        "title": "যে কাজগুলো করলে স্বয়ং রাসূল সা. জান্নাতের জিম্মাদার হবেন",
        "lecturer": "Ahmadullah",
        "length": "26:02",
        "lecturerId": "3"
    },
    {
        "itemId": "Ilc3b6A-epc",
        "title": "মৃত মা বাবার জন্য কোথায় দান করা উত্তম?",
        "lecturer": "Ahmadullah",
        "length": "08:25",
        "lecturerId": "3"
    },
    {
        "itemId": "t77zDkxP4ug",
        "title": "পর্দা যেভাবে নারীকে নিরাপত্তা প্রদান করে",
        "lecturer": "Ahmadullah",
        "length": "07:28",
        "lecturerId": "3"
    },
    {
        "itemId": "stBQfff1M98",
        "title": "আধুনিক বিশ্বে একজন নিবেদিত প্রাণ মুসলমান হতে কী করতে হবে?",
        "lecturer": "Ahmadullah",
        "length": "40:57",
        "lecturerId": "3"
    },
    {
        "itemId": "UhIgnIriI5o",
        "title": "দোয়া করার সুন্নাহ পদ্ধতি -ড. খোন্দকার আব্দুল্লাহ জাহাঙ্গীর",
        "lecturer": "Dr. Khandaker Abdullah Jahangir Rh",
        "length": "10:33",
        "lecturerId": "1"
    },
    {
        "itemId": "vmBbvfKDdoQ",
        "title": "সফল হওয়ার ক্ষেত্রে পালনীয় মূল ৪ টি বিষয় -ড. খোন্দকার আব্দুল্লাহ জাহাঙ্গীর",
        "lecturer": "Dr. Khandaker Abdullah Jahangir Rh",
        "length": "4:03",
        "lecturerId": "1"
    },
    {
        "itemId": "VBljg0QHSC0",
        "title": "শয়তানের পাঠশালার প্রথম পাঠ হলো 'হতাশা' -ড. খোন্দকার আব্দুল্লাহ জাহাঙ্গীর",
        "lecturer": "Dr. Khandaker Abdullah Jahangir Rh",
        "length": "18:31",
        "lecturerId": "1"
    }
]